{"context":"et_builder_layouts","data":{"23744338":{"ID":23744338,"post_date":"2026-07-07 13:13:10","post_date_gmt":"2026-07-07 13:13:10","post_content":"[et_pb_section fb_built=\"1\" custom_padding_last_edited=\"on|desktop\" _builder_version=\"4.27.5\" _module_preset=\"default\" custom_padding=\"80px||80px||true|false\" custom_padding_tablet=\"60px||60px||true|false\" custom_padding_phone=\"50px||50px||true|false\" global_colors_info=\"{}\" template_type=\"section\"][et_pb_row _builder_version=\"4.27.5\" _module_preset=\"default\" width=\"90%\" width_tablet=\"90%\" width_phone=\"90%\" width_last_edited=\"on|desktop\" custom_padding=\"0px||40px||false|false\" global_colors_info=\"{}\"][et_pb_column type=\"4_4\" _builder_version=\"4.27.5\" _module_preset=\"default\" global_colors_info=\"{}\"][et_pb_text _builder_version=\"4.27.5\" _module_preset=\"default\" header_text_align=\"center\" header_font_size=\"36px\" header_2_text_align=\"center\" header_2_font_size=\"36px\" header_3_text_align=\"center\" header_3_font_size=\"36px\" header_4_text_align=\"center\" header_4_font_size=\"36px\" header_5_text_align=\"center\" header_5_font_size=\"36px\" header_6_text_align=\"center\" header_6_font_size=\"36px\" background_enable_color=\"off\" header_font_size_tablet=\"34px\" header_font_size_phone=\"30px\" header_font_size_last_edited=\"on|desktop\" header_2_font_size_tablet=\"34px\" header_2_font_size_phone=\"30px\" header_2_font_size_last_edited=\"on|desktop\" header_3_font_size_tablet=\"34px\" header_3_font_size_phone=\"30px\" header_3_font_size_last_edited=\"on|desktop\" header_4_font_size_tablet=\"34px\" header_4_font_size_phone=\"30px\" header_4_font_size_last_edited=\"on|desktop\" header_5_font_size_tablet=\"34px\" header_5_font_size_phone=\"30px\" header_5_font_size_last_edited=\"on|desktop\" header_6_font_size_tablet=\"34px\" header_6_font_size_phone=\"30px\" header_6_font_size_last_edited=\"on|desktop\" global_colors_info=\"{}\"]<h2>Read Our Most <span style=\"color: #f4bd17;\">Frequently Asked Questions<\/span><\/h2>[\/et_pb_text][\/et_pb_column][\/et_pb_row][et_pb_row _builder_version=\"4.27.5\" _module_preset=\"default\" width=\"90%\" width_tablet=\"90%\" width_phone=\"90%\" width_last_edited=\"on|desktop\" custom_padding=\"0px||0px||true|false\" global_colors_info=\"{}\"][et_pb_column type=\"4_4\" _builder_version=\"4.27.5\" _module_preset=\"default\" global_colors_info=\"{}\"][et_pb_accordion open_toggle_text_color=\"#FFFFFF\" open_toggle_background_color=\"#F4BD17\" closed_toggle_text_color=\"#1F1F1F\" closed_toggle_background_color=\"#FFFFFF\" toggle_icon=\"&#xe04c;||divi||400\" icon_color=\"#1F1F1F\" module_class=\"pa-add-accordion-icon\" _builder_version=\"4.27.5\" _module_preset=\"default\" toggle_text_color=\"#3F3F3F\" toggle_font=\"|600|||||||\" toggle_font_size=\"22px\" body_text_color=\"#FFFFFF\" animation_style=\"slide\" animation_direction=\"bottom\" animation_intensity_slide=\"10%\" toggle_font_size_tablet=\"22px\" toggle_font_size_phone=\"22px\" toggle_font_size_last_edited=\"on|desktop\" border_radii=\"on|12px|12px|12px|12px\" border_color_all=\"#e0e0e0\" global_colors_info=\"{}\"][et_pb_accordion_item title=\"What is the minimum number of yards that I can purchase?\" open=\"on\" _builder_version=\"4.27.5\" _module_preset=\"default\" global_colors_info=\"{}\"]<p><span>25 cubic yards<\/span><\/p>[\/et_pb_accordion_item][et_pb_accordion_item title=\"How do I know how many yards I will need?  \" _builder_version=\"4.27.5\" _module_preset=\"default\" body_link_text_color=\"#FFFFFF\" global_colors_info=\"{}\" open=\"off\"]<p>Please use our <strong><a href=\"\/how-much-do-i-need\">Bark and Mulch Calculator<\/a><\/strong> to find out.<\/p>[\/et_pb_accordion_item][et_pb_accordion_item title=\"What is the delivery fee?\" _builder_version=\"4.27.5\" _module_preset=\"default\" global_colors_info=\"{}\" open=\"off\"]<p>Contact us for a Quote.\u00a0 Every job is different<\/p>[\/et_pb_accordion_item][et_pb_accordion_item title=\"What is your delivery area?\" _builder_version=\"4.27.5\" _module_preset=\"default\" global_colors_info=\"{}\" open=\"off\"]We currently service all of California. If you are in another state, please contact me for quote.[\/et_pb_accordion_item][et_pb_accordion_item title=\"Do you service homeowners? \" _builder_version=\"4.27.5\" _module_preset=\"default\" global_colors_info=\"{}\" open=\"off\"]<p>Yes, if you meet the 25 cubic yard minimum<\/p>[\/et_pb_accordion_item][\/et_pb_accordion][\/et_pb_column][\/et_pb_row][\/et_pb_section]","post_title":"FAQ-Section","post_excerpt":"","post_status":"publish","comment_status":"closed","ping_status":"closed","post_password":"","post_name":"faq-section","to_ping":"","pinged":"","post_modified":"2026-07-07 13:13:10","post_modified_gmt":"2026-07-07 13:13:10","post_content_filtered":"","post_parent":0,"menu_order":0,"post_type":"et_pb_layout","post_mime_type":"","comment_count":"0","filter":"raw","post_meta":{"_et_pb_built_for_post_type":["page"]},"terms":{"7":{"name":"not_global","slug":"not_global","taxonomy":"scope","parent":0,"all_parents":[],"description":""},"6":{"name":"regular","slug":"regular","taxonomy":"module_width","parent":0,"all_parents":[],"description":""},"10":{"name":"section","slug":"section","taxonomy":"layout_type","parent":0,"all_parents":[],"description":""}}}},"presets":"","global_colors":"","images":[],"thumbnails":[]}